pdover2t/__init__.py
pdover2t/misc.py
pdover2t/pipe_properties.py
pdover2t/dnvgl_rp_f109/__init__.py
pdover2t/dnvgl_rp_f109/absolute_stability.py
pdover2t/dnvgl_rp_f109/factor.py
pdover2t/dnvgl_st_f101/__init__.py
pdover2t/dnvgl_st_f101/factor.py
pdover2t/dnvgl_st_f101/loads_pressure.py
pdover2t/dnvgl_st_f101/material.py
pdover2t/dnvgl_st_f101/pipe_collapse.py
pdover2t/dnvgl_st_f101/pressure_containment.py
pdover2t/dnvgl_st_f101/propagation_buckling.py
pdover2t/dnvgl_st_f101/stability.py
pdover2t/metocean/__init__.py
pdover2t/metocean/wave.py
pdover2t-0.0.2.dist-info/LICENSE
pdover2t-0.0.2.dist-info/METADATA
pdover2t-0.0.2.dist-info/WHEEL
pdover2t-0.0.2.dist-info/top_level.txt
pdover2t-0.0.2.dist-info/RECORD
