Metadata-Version: 2.1
Name: pdover2t
Version: 0.0.2
Summary: Computational subsea pipeline engineering.
Home-page: https://github.com/qwilka/PDover2t
Author: Stephen McEntee
Author-email: stephenmce@gmail.com
License: MIT
Keywords: engineering computational
Platform: UNKNOWN
Classifier: Development Status :: 3 - Alpha
Classifier: License :: OSI Approved :: MIT License
Classifier: Programming Language :: Python :: 3.6
Classifier: Intended Audience :: Science/Research
Classifier: Topic :: Scientific/Engineering
Classifier: Natural Language :: English
Requires-Python: >=3.6
Requires-Dist: numpy
Requires-Dist: scipy
